dr_manhattan/__init__.py
dr_manhattan/base/__init__.py
dr_manhattan/base/errors.py
dr_manhattan/base/exchange.py
dr_manhattan/base/order_tracker.py
dr_manhattan/base/websocket.py
dr_manhattan/exchanges/__init__.py
dr_manhattan/exchanges/limitless.py
dr_manhattan/exchanges/polymarket.py
dr_manhattan/exchanges/polymarket_ws.py
dr_manhattan/models/__init__.py
dr_manhattan/models/crypto_hourly.py
dr_manhattan/models/market.py
dr_manhattan/models/nav.py
dr_manhattan/models/order.py
dr_manhattan/models/position.py
dr_manhattan/strategies/__init__.py
dr_manhattan/strategies/base.py
dr_manhattan/utils/__init__.py
dr_manhattan/utils/logger.py
dr_manhattan-0.0.1.dist-info/METADATA
dr_manhattan-0.0.1.dist-info/WHEEL
dr_manhattan-0.0.1.dist-info/RECORD
