Metadata-Version: 2.4
Name: dr-manhattan
Version: 0.0.1
Summary: CCXT-style unified API for prediction markets
Project-URL: Homepage, https://github.com/guzus/dr-manhattan
Project-URL: Repository, https://github.com/guzus/dr-manhattan
Project-URL: Issues, https://github.com/guzus/dr-manhattan/issues
Author: guzus
License-Expression: MIT
Keywords: api,ccxt,polymarket,prediction-markets,trading
Requires-Python: >=3.10
Requires-Dist: eth-account>=0.11.0
Requires-Dist: py-clob-client>=0.28.0
Requires-Dist: python-dotenv>=1.0.0
Requires-Dist: requests>=2.31.0
Requires-Dist: websockets>=15.0.1
